annotatable_properties/__init__.py
annotatable_properties/apps.py
annotatable_properties/managers.py
django_annotatable_properties-0.1.2.dist-info/LICENSE
django_annotatable_properties-0.1.2.dist-info/METADATA
django_annotatable_properties-0.1.2.dist-info/WHEEL
django_annotatable_properties-0.1.2.dist-info/top_level.txt
django_annotatable_properties-0.1.2.dist-info/RECORD
